{
  "Time": "29",
  "Title": "Strategy Tester Report",
  "EA Name": "EA31337-Advanced-21f4528279f99cd7e57a61281f258bc890d450e8",
  "Build": "1280",
  "Symbol": "EURUSD (Euro vs US Dollar)",
  "Period": "1 Minute (M1)  2019.01.01 23:42 - 2019.12.30 23:59    (2019.01.01 - 2019.12.31)",
  "Model": "Every tick ",
  "Initial deposit": "100000.00",
  "Spread": "10",
  "Modelling quality": "24.99%",
  "Parameters": "__EA_Mode_Parameters__=&#34;-- EA parameters for EA31337 Advanced v2.001 --&#34;; __Strategies_Active__=&#34;-- Active strategies --&#34;; Strategy_M1=0; Strategy_M5=0; Strategy_M15=23; Strategy_M30=23; __EA_Stops__=&#34;-- EA&#39;s stops --&#34;; EA_Stops_M1=0; EA_Stops_M5=0; EA_Stops_M15=28; EA_Stops_M30=28; __EA_Order_Params__=&#34;-- EA&#39;s order params --&#34;; EA_OrderCloseTime=-30; __Trade_Params__=&#34;-- EA&#39;s trade parameters --&#34;; EA_LotSize=0; EA_SignalOpenFilter=16; __EA_Risk_Params__=&#34;-- EA&#39;s risk management --&#34;; EA_Risk_MarginMax=10; __EA_Logging_Parameters__=&#34;-- Settings for logging &amp; messages --&#34;; VerboseLevel=3; __EA_Other_Parameters__=&#34;-- Other parameters --&#34;; EA_DisplayDetailsOnChart=true; ,EA_MagicNumber=31337; __EA_Parameters__=&#34;-- End of input parameters for EA31337 Advanced v2.001 --&#34;; ",
  "Bars in test": "371692",
  "Ticks modelled": "126198471",
  "Mismatched charts errors": "0",
  "Total net profit": "-13141.86",
  "Gross profit": "11288.54",
  "Gross loss": "-24430.40",
  "Profit factor": "0.46",
  "Expected payoff": "-17.83",
  "Absolute drawdown": "13141.86",
  "Maximal drawdown": "14961.06 (14.69%)",
  "Relative drawdown": "14.69% (14961.06)",
  "Total trades": "737",
  "Short positions": "361 (57.89%)",
  "Long positions": "376 (46.54%)",
  "Profit trades": "384 (52.10%)",
  "Loss trades": "353 (47.90%)",
  "profit trade": "164.80,29.40",
  "loss trade": "-200.80,-69.21",
  "consecutive wins (profit in money)": "36 (571.98)",
  "consecutive losses (loss in money)": "30 (-1646.48)",
  "consecutive profit": "1794.40 (35)",
  "consecutive loss": "30 (-1646.48),-2364.80 (26),11",
  "consecutive wins": "36 (571.98),12",
  "consecutive losses": "30 (-1646.48),11"
}
