{
  "Time": "37",
  "Title": "Strategy Tester Report",
  "EA Name": "EA31337-Rider-715cd760d37bb458677c83dec8edf1ff7c262d62",
  "Build": "1359",
  "Symbol": "EURUSD (Euro vs US Dollar)",
  "Period": "1 Minute (M1)  2020.01.01 23:41 - 2020.12.30 23:59    (2020.01.01 - 2020.12.31)",
  "Model": "Every tick ",
  "Initial deposit": "10000.00",
  "Spread": "1",
  "Modelling quality": "24.99%",
  "Parameters": "__EA_Params__=&#34;&gt;&gt; EA31337 Rider v3.000 build 1685406178 &lt;&lt;&#34;; __Strategies_Active__=&#34;-- Active strategies --&#34;; Strategy_M1=0; Strategy_M5=0; Strategy_M15=0; Strategy_M30=25; Strategy_H1=23; Strategy_H2=2; Strategy_H3=5; Strategy_H4=6; Strategy_H6=36; Strategy_H8=32; Strategy_H12=26; __Strategies_Stops__=&#34;-- Strategies&#39; stops --&#34;; EA_Stops_Strat=17; EA_Stops_Tf=720; __EA_Tasks__=&#34;-- EA&#39;s tasks --&#34;; EA_Task1_If=5; EA_Task1_Then=4; EA_Task2_If=4; EA_Task2_Then=4; EA_Task3_If=9; EA_Task3_Then=4; __Signal_Filters__=&#34;-- Signal filters --&#34;; EA_SignalOpenFilterMethod=37; EA_SignalCloseFilterMethod=40; EA_SignalOpenFilterTime=3; EA_TickFilterMethod=32; __EA_Risk_Params__=&#34;-- EA&#39;s risk management --&#34;; EA_Risk_MarginMax=1.20000005; __EA_Trade_Params__=&#34;-- EA&#39;s trade parameters --&#34;; EA_LotSize=0; EA_MagicNumber=31337; __Logging_Params__=&#34;-- EA&#39;s logging &amp; messaging --&#34;; VerboseLevel=1; EA_DisplayDetailsOnChart=true; ,",
  "Bars in test": "372155",
  "Ticks modelled": "167831773",
  "Mismatched charts errors": "0",
  "Total net profit": "-3734.03",
  "Gross profit": "53639.40",
  "Gross loss": "-57373.43",
  "Profit factor": "0.93",
  "Expected payoff": "-2.23",
  "Absolute drawdown": "3745.63",
  "Maximal drawdown": "24701.53 (79.80%)",
  "Relative drawdown": "79.80% (24701.53)",
  "Total trades": "1675",
  "Short positions": "825 (37.21%)",
  "Long positions": "850 (52.24%)",
  "Profit trades": "751 (44.84%)",
  "Loss trades": "924 (55.16%)",
  "profit trade": "275.09,71.42",
  "loss trade": "-328.03,-62.09",
  "consecutive wins (profit in money)": "33 (4764.75)",
  "consecutive losses (loss in money)": "21 (-1654.68)",
  "consecutive profit": "4944.83 (22)",
  "consecutive loss": "21 (-1654.68),-3484.57 (17),4",
  "consecutive wins": "33 (4764.75),3",
  "consecutive losses": "21 (-1654.68),4"
}
