{
  "Time": "41",
  "Title": "Strategy Tester Report",
  "EA Name": "EA31337-Rider-3a3d062454d0c7470939c3dbb96d72d53af60407",
  "Build": "1320",
  "Symbol": "EURUSD (Euro vs US Dollar)",
  "Period": "1 Minute (M1)  2018.01.01 23:40 - 2018.12.30 23:59    (2018.01.01 - 2018.12.31)",
  "Model": "Every tick ",
  "Initial deposit": "100000.00",
  "Spread": "1",
  "Modelling quality": "24.99%",
  "Parameters": "__EA_Params__=&#34;&gt;&gt; EA31337 Rider v2.006 build 1632158493 &lt;&lt;&#34;; __Strategies_Active__=&#34;-- Active strategies --&#34;; Strategy_M1=0; Strategy_M5=0; Strategy_M15=1; Strategy_M30=14; Strategy_H1=24; Strategy_H2=9; Strategy_H3=5; Strategy_H4=27; __Strategies_Stops__=&#34;-- Strategies&#39; stops --&#34;; EA_Stops_Strat=13; EA_Stops_Tf=480; __EA_Tasks__=&#34;-- EA&#39;s tasks --&#34;; EA_Task1_If=2; EA_Task1_Then=2; EA_Task2_If=3; EA_Task2_Then=2; EA_Task3_If=6; EA_Task3_Then=5; __Strategies_Filters__=&#34;-- Strategies&#39; filters --&#34;; EA_SignalOpenFilterMethod=32; EA_SignalCloseFilter=32; EA_SignalOpenFilterTime=3; EA_TickFilterMethod=60; __EA_Risk_Params__=&#34;-- EA&#39;s risk management --&#34;; EA_Risk_MarginMax=1.20000005; __EA_Trade_Params__=&#34;-- EA&#39;s trade parameters --&#34;; EA_LotSize=0; EA_MagicNumber=31337; __Logging_Params__=&#34;-- EA&#39;s logging &amp; messaging --&#34;; VerboseLevel=1; EA_DisplayDetailsOnChart=true; ,",
  "Bars in test": "356589",
  "Ticks modelled": "109229002",
  "Mismatched charts errors": "0",
  "Total net profit": "-8594.07",
  "Gross profit": "67670.08",
  "Gross loss": "-76264.15",
  "Profit factor": "0.89",
  "Expected payoff": "-3.91",
  "Absolute drawdown": "13064.02",
  "Maximal drawdown": "15631.69 (15.24%)",
  "Relative drawdown": "15.24% (15631.69)",
  "Total trades": "2197",
  "Short positions": "904 (53.76%)",
  "Long positions": "1293 (36.12%)",
  "Profit trades": "953 (43.38%)",
  "Loss trades": "1244 (56.62%)",
  "profit trade": "777.04,71.01",
  "loss trade": "-473.99,-61.31",
  "consecutive wins (profit in money)": "14 (1041.75)",
  "consecutive losses (loss in money)": "18 (-2925.52)",
  "consecutive profit": "1677.79 (12)",
  "consecutive loss": "18 (-2925.52),-2925.52 (18),3",
  "consecutive wins": "14 (1041.75),2",
  "consecutive losses": "18 (-2925.52),3"
}
